aws_codestar_cdk/__init__.py
aws_codestar_cdk/lambda_codestar.py
aws_codestar_cdk/custom/__init__.py
aws_codestar_cdk/custom/codestar_project.py
aws_codestar_cdk/files/source.zip
aws_codestar_cdk/files/toolchain.yml
aws_codestar_cdk/parameters/__init__.py
aws_codestar_cdk/parameters/codestar_lambda_parameters.py
aws_codestar_cdk/parameters/deployment_parameters.py
aws_codestar_cdk/parameters/lambda_type_parameters.py
aws_codestar_cdk/parameters/vpc_parameters.py
aws_codestar_cdk-4.1.0.dist-info/LICENSE
aws_codestar_cdk-4.1.0.dist-info/METADATA
aws_codestar_cdk-4.1.0.dist-info/WHEEL
aws_codestar_cdk-4.1.0.dist-info/top_level.txt
aws_codestar_cdk-4.1.0.dist-info/RECORD
